mempool/__init__.py
mempool/api.py
python_mempool_api-1.0.0b0.dist-info/METADATA
python_mempool_api-1.0.0b0.dist-info/WHEEL
python_mempool_api-1.0.0b0.dist-info/top_level.txt
python_mempool_api-1.0.0b0.dist-info/RECORD
