Metadata-Version: 2.1
Name: python-mempool-api
Version: 1.0.0b0
Summary: A Python package for mempool.space REST API interaction.
Author: k0g1t0
Keywords: python,bitcoin,mempool,api
Classifier: Intended Audience :: Developers
Classifier: Programming Language :: Python :: 3
Classifier: Operating System :: Unix
Classifier: Operating System :: MacOS :: MacOS X
Classifier: Operating System :: Microsoft :: Windows
Requires-Dist: requests
